.testr.conf
AUTHORS
ChangeLog
LICENSE
README.rst
requirements.txt
setup.cfg
setup.py
test-requirements.txt
tox.ini
doc/source/conf.py
doc/source/index.rst
doc/source/pycmus.rst
doc/source/readme.rst
pycmus/__init__.py
pycmus/exceptions.py
pycmus/remote.py
pycmus.egg-info/PKG-INFO
pycmus.egg-info/SOURCES.txt
pycmus.egg-info/dependency_links.txt
pycmus.egg-info/not-zip-safe
pycmus.egg-info/pbr.json
pycmus.egg-info/requires.txt
pycmus.egg-info/top_level.txt
pycmus/tests/__init__.py