Metadata-Version: 1.1
Name: pycmus
Version: 0.0.3
Summary: A python cmus remote library
Home-page: UNKNOWN
Author: Matthew Treinish
Author-email: mtreinish@kortar.org
License: UNKNOWN
Platform: UNKNOWN
Classifier: License :: OSI Approved :: GNU General Public License v3 (GPLv3)
Classifier: Programming Language :: Python
Classifier: Programming Language :: Python :: 2
Classifier: Programming Language :: Python :: 2.7
Classifier: Programming Language :: Python :: 3
Classifier: Programming Language :: Python :: 3.4
Classifier: Programming Language :: Python :: 3.5
